[{"data":"2026-07-24","sc":{"AAZQ11":51,"ABCP11":38,"AFHF11":40,"AFHI11":47,"AGRX11":73,"AIEC11":40,"AJFI11":38,"ALZC11":44,"ALZR11":38,"APXM11":44,"AROA11":88,"ARRI11":44,"ARXD11":44,"AZPL11":34,"BBFO11":30,"BBGO11":42,"BBIG11":38,"BBRC11":53,"BCIA11":30,"BCRI11":76,"BDIF11":43,"BIDB11":42,"BIME11":40,"BINC11":42,"BLCA11":40,"BLMG11":34,"BMLC11":55,"BNFS11":37,"BODB11":35,"BPML11":38,"BRCO11":34,"BRCR11":40,"BRFT11":48,"BROF11":40,"BSLT11":40,"BTAG11":48,"BTAL11":38,"BTCI11":44,"BTHF11":40,"BTLG11":32,"BTRA11":54,"CACR11":84,"CCME11":40,"CDII11":43,"CEOC11":40,"CLIN11":47,"CNES11":40,"CPLG11":34,"CPOF11":40,"CPSH11":38,"CPTI11":35,"CPTR11":58,"CPTS11":40,"CPUR11":36,"CRAA11":42,"CRFF11":30,"CXAG11":37,"CXCI11":38,"CXCO11":40,"CXRI11":30,"CYCR11":68,"DCRA11":42,"DEVA11":76,"DIVS11":35,"DVFF11":30,"EGAF11":42,"EIRA11":44,"EMET11":40,"EQIR11":44,"EURO11":34,"EXES11":76,"FAED11":39,"FAMB11":48,"FATN11":40,"FCFL11":39,"FGAA11":42,"FIGS11":38,"FIIB11":34,"FIIP11":38,"FLCR11":47,"FLMA11":40,"FLRP11":54,"FTCA11":73,"FVPQ11":46,"FYTO11":44,"GAME11":44,"GARE11":40,"GCRA11":60,"GCRI11":44,"GGRC11":34,"GRUL11":34,"GSFI11":38,"GSRF11":88,"GTWR11":40,"GZIT11":44,"HABT11":44,"HCRI11":38,"HCTR11":84,"HFOF11":46,"HGBS11":38,"HGCR11":44,"HGLG11":32,"HGRE11":40,"HGRU11":36,"HLOG11":42,"HOFC11":55,"HPDP11":38,"HREC11":44,"HSAF11":44,"HSLG11":34,"HSML11":54,"HSRE11":38,"HTMX11":40,"IAAG11":58,"IBBP11":34,"IBCR11":60,"ICNE11":54,"ICRI11":53,"IFRA11":35,"IFRI11":35,"INLG11":50,"INRD11":39,"IRIF11":35,"IRIM11":44,"ITIP11":40,"ITIT11":40,"ITRI11":40,"JCCJ11":30,"JFLL11":39,"JGPX11":82,"JMBI11":42,"JPPA11":44,"JSAF11":30,"JSCR11":44,"JSRE11":40,"JURO11":43,"KCRE11":49,"KDIF11":35,"KDOL11":42,"KFOF11":35,"KISU11":30,"KIVO11":80,"KNCA11":42,"KNCR11":42,"KNHF11":40,"KNHY11":50,"KNIP11":42,"KNRI11":43,"KNSC11":44,"KNUQ11":44,"KOPA11":42,"KORE11":44,"LASC11":38,"LIFE11":44,"LSAG11":60,"LVBI11":34,"MANA11":44,"MAXR11":51,"MCCI11":44,"MCRE11":40,"MFII11":53,"MXRF11":42,"NAVT11":30,"NEWL11":34,"NEXG11":42,"NSLU11":38,"OGIN11":35,"OIAG11":42,"OUJP11":60,"OXRL11":54,"PATC11":48,"PCIP11":60,"PLAG11":36,"PLCA11":42,"PMIS11":44,"PMLL11":38,"PORD11":44,"PQAG11":40,"PQDP11":38,"PSEC11":40,"PVBI11":48,"RBFM11":40,"RBHG11":44,"RBHY11":44,"RBIF11":42,"RBIR11":53,"RBRD11":36,"RBRL11":34,"RBRP11":38,"RBRR11":44,"RBRS11":39,"RBRX11":42,"RBRY11":44,"RBVA11":36,"RCRB11":40,"RCRI11":44,"RECM11":58,"RECR11":44,"RECT11":40,"RIFF11":35,"RINV11":30,"RNGO11":40,"RPRI11":44,"RURA11":42,"RZAG11":42,"RZAK11":47,"RZAT11":38,"RZLC11":42,"RZTR11":52,"RZZR11":34,"SAPI11":53,"SEQR11":38,"SHOP11":44,"SHPH11":43,"SHPP11":48,"SMRE11":56,"SNAG11":42,"SNCI11":76,"SNEL11":40,"SNFF11":30,"SNFZ11":36,"SNID11":43,"SNME11":49,"SPTW11":40,"SPXS11":44,"STYI11":54,"TEPP11":40,"TGAR11":53,"TJKB11":54,"TMPS11":30,"TOPP11":40,"TRBL11":34,"TRXB11":36,"TRXF11":33,"TRXY11":40,"TVRI11":37,"URPR11":68,"VCJR11":44,"VCRA11":58,"VCRI11":76,"VCRR11":39,"VGHF11":42,"VGIA11":68,"VGIP11":47,"VGIR11":44,"VGRI11":40,"VILG11":34,"VINO11":40,"VISC11":38,"VIUR11":36,"VOTS11":44,"VPPR11":48,"VRTA11":60,"VRTM11":40,"VSHO11":38,"VSLH11":76,"VVCR11":44,"VVRI11":38,"VXXV11":50,"WHGR11":44,"XLPR11":44,"XPCA11":42,"XPCI11":68,"XPID11":59,"XPIN11":50,"XPLG11":39,"XPML11":36,"XPSF11":38,"ZAGH11":40,"ZAVI11":38,"PFIN11":60,"XPIE11":60,"BRZP11":60,"KNOX11":60,"VIGT11":60,"ENDD11":60,"BDIV11":60,"KNDI11":60,"PPEI11":60,"AZIN11":60,"COPN11":60}}]